[
  {
    "QuestionPart1": "Ich",
    "QuestionPart2": "(kommen) aus Österreich.",
    "QuestionPart3": "",
    "AnswerPart1": "komme",
    "AnswerPart2": "",
    "AnswerPart3": ""
  },
  {
    "QuestionPart1": "Mein Vater",
    "QuestionPart2": "(arbeiten) in einem Büro in der Innenstadt.",
    "QuestionPart3": "",
    "AnswerPart1": "arbeitet",
    "AnswerPart2": "",
    "AnswerPart3": ""
  },
  {
    "QuestionPart1": "Marko",
    "QuestionPart2": "(gehen) in die Schule.",
    "QuestionPart3": "",
    "AnswerPart1": "geht",
    "AnswerPart2": "",
    "AnswerPart3": ""
  },
  {
    "QuestionPart1": "Ana und Iva",
    "QuestionPart2": "(lernen) Deutsch.",
    "QuestionPart3": "",
    "AnswerPart1": "lernen",
    "AnswerPart2": "",
    "AnswerPart3": ""
  },
  {
    "QuestionPart1": "Ihr",
    "QuestionPart2": "(trinken) jeden Morgen Kaffee.",
    "QuestionPart3": "",
    "AnswerPart1": "trinkt",
    "AnswerPart2": "",
    "AnswerPart3": ""
  },
  {
    "QuestionPart1": "Ich",
    "QuestionPart2": "(lieben) meine Mutter.",
    "QuestionPart3": "",
    "AnswerPart1": "liebe",
    "AnswerPart2": "",
    "AnswerPart3": ""
  },
  {
    "QuestionPart1": "Mein Bruder",
    "QuestionPart2": "(kaufen) jeden Morgen Brot.",
    "QuestionPart3": "",
    "AnswerPart1": "kauft",
    "AnswerPart2": "",
    "AnswerPart3": ""
  },
  {
    "QuestionPart1": "Meine Eltern",
    "QuestionPart2": "(spazieren) jeden Abend im Park.",
    "QuestionPart3": "",
    "AnswerPart1": "spazieren",
    "AnswerPart2": "",
    "AnswerPart3": ""
  },
  {
    "QuestionPart1": "Du",
    "QuestionPart2": "(helfen) mir immer, meine Hausaufgaben zu machen.",
    "QuestionPart3": "",
    "AnswerPart1": "hilfst",
    "AnswerPart2": "",
    "AnswerPart3": ""
  },
  {
    "QuestionPart1": "Was",
    "QuestionPart2": "(machen) du jetzt?",
    "QuestionPart3": "",
    "AnswerPart1": "machst",
    "AnswerPart2": "",
    "AnswerPart3": ""
  },
  {
    "QuestionPart1": "Ich und mein Bruder",
    "QuestionPart2": "(spielen) Fußball.",
    "QuestionPart3": "",
    "AnswerPart1": "spielen",
    "AnswerPart2": "",
    "AnswerPart3": ""
  },
  {
    "QuestionPart1": "",
    "QuestionPart2": "(laufen) du jede Woche? ",
    "QuestionPart3": "",
    "AnswerPart1": "Läufst",
    "AnswerPart2": "",
    "AnswerPart3": ""
  },
  {
    "QuestionPart1": "",
    "QuestionPart2": "(spielen) du Basketball?",
    "QuestionPart3": "",
    "AnswerPart1": "Spielst",
    "AnswerPart2": "",
    "AnswerPart3": ""
  },
  {
    "QuestionPart1": "Ich",
    "QuestionPart2": "(trinken) gerne Tee.",
    "QuestionPart3": "",
    "AnswerPart1": "trinke",
    "AnswerPart2": "",
    "AnswerPart3": ""
  },
  {
    "QuestionPart1": "Er",
    "QuestionPart2": "(reden) nicht gerne darüber.",
    "QuestionPart3": "",
    "AnswerPart1": "redet",
    "AnswerPart2": "",
    "AnswerPart3": ""
  },
  {
    "QuestionPart1": "Sie",
    "QuestionPart2": "(antwortet) nie auf alle Nachrichten.",
    "QuestionPart3": "",
    "AnswerPart1": "antwortet",
    "AnswerPart2": "",
    "AnswerPart3": ""
  },
  {
    "QuestionPart1": "Er",
    "QuestionPart2": "(laufen) jeden Tag fünf Kilometer.",
    "QuestionPart3": "",
    "AnswerPart1": "läuft",
    "AnswerPart2": "",
    "AnswerPart3": ""
  },
  {
    "QuestionPart1": "Du",
    "QuestionPart2": "(tragen) immer schwarze Röcke.",
    "QuestionPart3": "",
    "AnswerPart1": "trägst",
    "AnswerPart2": "",
    "AnswerPart3": ""
  },
  {
    "QuestionPart1": "Meine Schwester",
    "QuestionPart2": "(helfen) mir immer dabei.",
    "QuestionPart3": "",
    "AnswerPart1": "hilft",
    "AnswerPart2": "",
    "AnswerPart3": ""
  }
]